ansible_kernel/__init__.py
ansible_kernel/__main__.py
ansible_kernel/convert_playbook.py
ansible_kernel/install.py
ansible_kernel/kernel.py
ansible_kernel/module_args.py
ansible_kernel/module_args.yml
ansible_kernel/modules.py
ansible_kernel/modules.yml
ansible_kernel/play_args.py
ansible_kernel/task_args.py
ansible_kernel/update_module_cache.py
ansible_kernel/widgets.py
ansible_kernel/exporters/__init__.py
ansible_kernel/exporters/ansible_playbook.py
ansible_kernel/exporters/ansible_tasks.py
ansible_kernel/exporters/ansible_zip.py
ansible_kernel/plugins/__init__.py
ansible_kernel/plugins/callback/__init__.py
ansible_kernel/plugins/callback/ansible_kernel_helper.py
ansible_kernel/roles/__init__.py
ansible_kernel/roles/ansible_kernel_helpers/__init__.py
ansible_kernel/roles/ansible_kernel_helpers/action_plugins/__init__.py
ansible_kernel/roles/ansible_kernel_helpers/action_plugins/pause_for_kernel.py
ansible_kernel/roles/ansible_kernel_helpers/library/__init__.py
ansible_kernel/roles/ansible_kernel_helpers/library/pause_for_kernel.py
ansible_kernel/templates/ansible_playbook.tpl
ansible_kernel/templates/ansible_tasks.tpl
ansible_kernel-0.9.0.dist-info/LICENSE.txt
ansible_kernel-0.9.0.dist-info/METADATA
ansible_kernel-0.9.0.dist-info/RECORD
ansible_kernel-0.9.0.dist-info/WHEEL
ansible_kernel-0.9.0.dist-info/entry_points.txt
ansible_kernel-0.9.0.dist-info/top_level.txt
