Metadata-Version: 2.1
Name: ansible-kernel
Version: 0.9.0
Summary: An Ansible kernel for Jupyter
Home-page: UNKNOWN
Author: UNKNOWN
Author-email: UNKNOWN
License: Apache
Platform: UNKNOWN
Requires-Dist: ansible
Requires-Dist: ansible-runner (>=1.1.0)
Requires-Dist: PyYAML
Requires-Dist: psutil
Requires-Dist: jupyter
Requires-Dist: tqdm
Requires-Dist: docopt
Requires-Dist: six
Requires-Dist: ipywidgets
